{
  "db_name": "PostgreSQL",
  "query": "\n        INSERT INTO workflows (owner_id, name, description, graph)\n        VALUES ($1, $2, $3, $4)\n        RETURNING *\n        ",
  "describe": {
    "columns": [
      {
        "ordinal": 0,
        "name": "id",
        "type_info": "Uuid"
      },
      {
        "ordinal": 1,
        "name": "owner_id",
        "type_info": "Uuid"
      },
      {
        "ordinal": 2,
        "name": "name",
        "type_info": "Text"
      },
      {
        "ordinal": 3,
        "name": "description",
        "type_info": "Text"
      },
      {
        "ordinal": 4,
        "name": "graph",
        "type_info": "Jsonb"
      },
      {
        "ordinal": 5,
        "name": "tags",
        "type_info": "TextArray"
      },
      {
        "ordinal": 6,
        "name": "is_public",
        "type_info": "Bool"
      },
      {
        "ordinal": 7,
        "name": "created_at",
        "type_info": "Timestamptz"
      },
      {
        "ordinal": 8,
        "name": "updated_at",
        "type_info": "Timestamptz"
      }
    ],
    "parameters": {
      "Left": [
        "Uuid",
        "Text",
        "Text",
        "Jsonb"
      ]
    },
    "nullable": [
      false,
      false,
      false,
      true,
      false,
      true,
      false,
      false,
      false
    ]
  },
  "hash": "3b402b7f40b9184985f66c86497bb6fadbfe9efa3845426cc496ff21bd31de90"
}
